blueque/__init__.py
blueque/client.py
blueque/forking_runner.py
blueque/listener.py
blueque/process_helpers.py
blueque/processor.py
blueque/queue.py
blueque/redis_queue.py
blueque/redis_task.py
blueque/task.py
blueque-1.0.0.dist-info/LICENSE
blueque-1.0.0.dist-info/METADATA
blueque-1.0.0.dist-info/WHEEL
blueque-1.0.0.dist-info/RECORD
