Metadata-Version: 2.1
Name: blueque
Version: 1.0.0
Summary: Simple job queueing for very long tasks
License: Apache-2.0
Author: uStudio Developers
Author-email: dev@ustudio.com
Requires-Python: >=3.9,<4.0
Classifier: License :: OSI Approved :: Apache Software License
Classifier: Programming Language :: Python :: 3
Classifier: Programming Language :: Python :: 3.9
Classifier: Programming Language :: Python :: 3.10
Classifier: Programming Language :: Python :: 3.11
Requires-Dist: redis (>=5.0.1,<6.0.0)
